LICENSE.rst
MANIFEST.in
README.md
requirements.txt
setup.cfg
setup.py
charactr_api/__init__.py
charactr_api/sdk/__init__.py
charactr_api/sdk/clones.py
charactr_api/sdk/config.py
charactr_api/sdk/conversion_module.py
charactr_api/sdk/data_objects.py
charactr_api/sdk/errors.py
charactr_api/sdk/sdk.py
charactr_api/sdk/streaming_utils.py
charactr_api/sdk/tts.py
charactr_api/sdk/tts_stream_duplex.py
charactr_api/sdk/tts_stream_simplex.py
charactr_api/sdk/vc.py
charactr_api_sdk.egg-info/PKG-INFO
charactr_api_sdk.egg-info/SOURCES.txt
charactr_api_sdk.egg-info/dependency_links.txt
charactr_api_sdk.egg-info/requires.txt
charactr_api_sdk.egg-info/top_level.txt