Metadata-Version: 2.1
Name: charactr-api-sdk
Version: 2.1.0
Summary: Python SDK to interact with the charactr API.
Home-page: https://github.com/charactr-platform/charactr-api-sdk-python
Author: charactr
Author-email: support@gemelo.ai
Requires-Python: >=3.9.0
License-File: LICENSE.rst
